apostrofo_models_sdk/__init__.py
apostrofo_models_sdk/client.py
apostrofo_models_sdk/constants.py
apostrofo_models_sdk/exceptions.py
apostrofo_models_sdk/models.py
apostrofo_models_sdk-0.1.0.dist-info/METADATA
apostrofo_models_sdk-0.1.0.dist-info/WHEEL
apostrofo_models_sdk-0.1.0.dist-info/top_level.txt
apostrofo_models_sdk-0.1.0.dist-info/RECORD
